.codecov.yml
.dockerignore
.flake8
.pylintrc
.readthedocs.yml
AUTHORS
CONTRIBUTING.rst
ChangeLog
Dockerfile.faucet
Dockerfile.fuzz-config
Dockerfile.fuzz-packet
Dockerfile.gauge
Dockerfile.tests
LICENSE
Makefile
README.rst
codecheck-requirements.txt
docker-compose.yaml
fuzz-requirements.txt
helper-funcs
hw_switch_config.yaml
requirements.txt
setup.cfg
setup.py
test-requirements.txt
.github/dependabot.yml
.github/renovate.json
.github/workflows/periodic.yml
.github/workflows/release-debian.yml
.github/workflows/release-docker.yml
.github/workflows/release-python.yml
.github/workflows/tests-codecheck.yml
.github/workflows/tests-docs.yml
.github/workflows/tests-integration.yml
.github/workflows/tests-unit.yml
.github/workflows/tests-yaml-lint.yml
adapters/README.rst
adapters/vendors/faucetagent/Dockerfile
adapters/vendors/faucetagent/README.rst
adapters/vendors/faucetagent/docker-compose.yaml
adapters/vendors/faucetagent/example_client.sh
adapters/vendors/faucetagent/gencerts.sh
adapters/vendors/faucetagent/requirements.txt
adapters/vendors/rabbitmq/Dockerfile
adapters/vendors/rabbitmq/README.rst
adapters/vendors/rabbitmq/docker-compose-rabbitmq.yaml
adapters/vendors/rabbitmq/docker-compose.yaml
adapters/vendors/rabbitmq/example_consumer.py
adapters/vendors/rabbitmq/rabbit.py
adapters/vendors/rabbitmq/requirements.txt
adapters/vendors/rabbitmq/test_rabbit.py
adapters/vendors/rabbitmq/hooks/pre_build
clib/__init__.py
clib/clib_mininet_test.py
clib/clib_mininet_test_main.py
clib/clib_mininet_tests.py
clib/config_generator.py
clib/docker_host.py
clib/fakeoftable.py
clib/mininet_test_base.py
clib/mininet_test_base_topo.py
clib/mininet_test_topo.py
clib/mininet_test_util.py
clib/mininet_test_watcher.py
clib/tcpdump_helper.py
clib/valve_test_lib.py
debian/changelog
debian/compat
debian/control
debian/copyright
debian/faucet-all-in-one.install
debian/faucet-docs.docs
debian/faucet.default
debian/faucet.install
debian/faucet.postinst
debian/faucet.service
debian/gauge.default
faucet.egg-info/PKG-INFO
faucet.egg-info/SOURCES.txt
faucet.egg-info/dependency_links.txt
faucet.egg-info/entry_points.txt
faucet.egg-info/not-zip-safe
faucet.egg-info/pbr.json
faucet.egg-info/requires.txt
faucet.egg-info/top_level.txt
