Metadata-Version: 2.1
Name: faucet
Version: 1.10.11
Summary: Faucet is an OpenFlow controller that implements a layer 2 and layer 3 switch.
Home-page: https://faucet.nz
Author: Faucet development team
Author-email: faucetsdn@googlegroups.com
License: Apache-2
Keywords: openflow,openvswitch,ryu
Platform: any
Classifier: Development Status :: 5 - Production/Stable
Classifier: License :: OSI Approved :: Apache Software License
Classifier: Topic :: System :: Networking
Classifier: Natural Language :: English
Classifier: Programming Language :: Python
Classifier: Programming Language :: Python :: 3.8
Classifier: Programming Language :: Python :: 3.9
Classifier: Programming Language :: Python :: 3.10
Classifier: Operating System :: Unix
Requires-Python: >=3.8
License-File: LICENSE
License-File: AUTHORS
